cowtool/__init__.py
cowtool/converter.py
cowtool/headers_format.py
cowtool-0.0.2.dist-info/LICENSE
cowtool-0.0.2.dist-info/METADATA
cowtool-0.0.2.dist-info/WHEEL
cowtool-0.0.2.dist-info/entry_points.txt
cowtool-0.0.2.dist-info/top_level.txt
cowtool-0.0.2.dist-info/RECORD
