Metadata-Version: 2.1
Name: cowtool
Version: 0.0.2
Summary: 实用工具库
Home-page: 
Author: Linjie Xing
Author-email: 
License: UNKNOWN
Platform: UNKNOWN
Classifier: Programming Language :: Python :: 3
Classifier: License :: OSI Approved :: MIT License
Classifier: Operating System :: OS Independent
License-File: LICENSE
